Metadata-Version: 1.0
Name: miniseq
Version: 0.3
Summary: Minimal sequence classes
Home-page: http://github.com/scastlara/miniseq
Author: S. Castillo-Lara
Author-email: sergiocastillo@ub.edu
License: GPL-3.0
Platform: UNKNOWN
